entity_resolution_evaluation/__init__.py
entity_resolution_evaluation/evaluation.py
entity_resolution_evaluation/reconcile.py
entity_resolution_evaluation/test.py
entity_resolution_evaluation-0.0.2.dist-info/LICENSE
entity_resolution_evaluation-0.0.2.dist-info/METADATA
entity_resolution_evaluation-0.0.2.dist-info/WHEEL
entity_resolution_evaluation-0.0.2.dist-info/top_level.txt
entity_resolution_evaluation-0.0.2.dist-info/RECORD
