Metadata-Version: 2.1
Name: entity-resolution-evaluation
Version: 0.0.2
Summary: An implementation of the generalized merged distance to evaluate entity resolution
Home-page: https://github.com/entrepreneur-interet-general/entity-resolution-evaluation
Author: Paul Boosz
Author-email: paulboosz@gmail.com
License: UNKNOWN
Platform: UNKNOWN
Classifier: Programming Language :: Python :: 3
Classifier: License :: OSI Approved :: MIT License
Classifier: Operating System :: OS Independent
